README.md
prioheap.py
setup.py
prioheap.egg-info/PKG-INFO
prioheap.egg-info/SOURCES.txt
prioheap.egg-info/dependency_links.txt
prioheap.egg-info/top_level.txt