Metadata-Version: 2.1
Name: prioheap
Version: 0.0.2
Summary: Priority queue with a sane API
Home-page: https://github.com/adefossez/prioheap
Author: Alexandre Défossez
Author-email: alexandre.defossez@gmail.com
License: Unlicense license
Platform: UNKNOWN
Classifier: Topic :: Text Processing
Requires-Python: >=3.6.0
